Metadata-Version: 2.1
Name: textgameengine
Version: 0.39
Summary: A game engine made in python which uses text as its graphic interface instead of regular 2d shapes and sprites.
Home-page: https://github.com/toasterstrudelz/Text-Based-Game-Engine
Author: Daniel Pagano
Author-email: danielpagano202@gmail.com
License: MIT
Download-URL: https://github.com/toasterstrudelz/Text-Based-Game-Engine/archive/refs/tags/v_0.5.tar.gz
Keywords: Python,Text,Game-Engine
Platform: UNKNOWN
Classifier: Development Status :: 3 - Alpha
Classifier: Intended Audience :: Developers
Classifier: Topic :: Software Development :: Build Tools
Classifier: License :: OSI Approved :: MIT License
Classifier: Programming Language :: Python :: 3.6
Classifier: Programming Language :: Python :: 3.7
Classifier: Programming Language :: Python :: 3.8
Classifier: Programming Language :: Python :: 3.9
License-File: LICENSE.txt
